izihawa_configurator/__init__.py
izihawa_configurator/exceptions.py
izihawa_configurator-1.1.0.dist-info/licenses/LICENSE
izihawa_configurator-1.1.0.dist-info/METADATA
izihawa_configurator-1.1.0.dist-info/WHEEL
izihawa_configurator-1.1.0.dist-info/top_level.txt
izihawa_configurator-1.1.0.dist-info/RECORD
