Metadata-Version: 2.4
Name: izihawa-configurator
Version: 1.1.0
Summary: A library for reading YAML configs and overriding values from environment variables
Author: Izihawa
License: MIT License
Requires-Python: >=3.8
License-File: LICENSE
Requires-Dist: PyYAML
Requires-Dist: Jinja2
Requires-Dist: izihawa-utils
Provides-Extra: dev
Requires-Dist: pytest; extra == "dev"
Requires-Dist: pytest-cov; extra == "dev"
Dynamic: license-file
